lipsgit/__init__.py
lipsgit/__main__.py
lipsgit/console.py
lipsgit/defaults.py
lipsgit/exceptions.py
lipsgit/git.py
lipsgit/matching.py
lipsgit/models.py
lipsgit/storage.py
lipsgit-0.1.2.dist-info/LICENSE
lipsgit-0.1.2.dist-info/METADATA
lipsgit-0.1.2.dist-info/WHEEL
lipsgit-0.1.2.dist-info/entry_points.txt
lipsgit-0.1.2.dist-info/RECORD
